coregen/__init__.py
coregen/exceptions.py
coregen-0.1.2.dist-info/AUTHORS.rst
coregen-0.1.2.dist-info/LICENSE
coregen-0.1.2.dist-info/METADATA
coregen-0.1.2.dist-info/WHEEL
coregen-0.1.2.dist-info/top_level.txt
coregen-0.1.2.dist-info/RECORD
