Metadata-Version: 2.1
Name: coregen
Version: 0.1.2
Summary: Library for generic functions
Home-page: https://github.com/coregen/coregen
Author: Barak Avrahami
Author-email: barak1345@gmail.com
License: MIT license
Keywords: coregen
Platform: UNKNOWN
Classifier: Development Status :: 2 - Pre-Alpha
Classifier: Intended Audience :: Developers
Classifier: License :: OSI Approved :: MIT License
Classifier: Natural Language :: English
Classifier: Programming Language :: Python :: 3
Classifier: Programming Language :: Python :: 3.5
Classifier: Programming Language :: Python :: 3.6
Classifier: Programming Language :: Python :: 3.7
Requires-Python: >3.5
